Workbook

Sheet Input
A1: Input Details Here
A2: Date : | B2: October 13, 2026 | F2: Editable | G2: Qty. | H2: Unit | I2: Description | J2: Unit Price | K2: Amount
A3: Company Name : | B3: TRUE-TEMP CORPORATION | F3: Editable | G3: 300 | H3: Pcs | I3: 6" TDC Cleat Material: G.I. | J3: 10 | K3: =J3*G3 -> 3000 | M3: For Sales Invoice | P3: =J3*0.12 -> 1.2 | Q3: =J3+P3 -> 11.2 | R3: =Q3*0.95 -> 10.64
A4: TIN # : | B4: 216-506-486-00000 | F4: Editable | G4: 500 | H4: Pcs | I4: Angle Corner Material:G.I. / GA20 | J4: 8 | K4: =J4*G4 -> 4000 | M4: up to 7 lines only | P4: =J4*0.12 -> 0.96 | Q4: =J4+P4 -> 8.96 | R4: =Q4*0.95 -> 8.512
A5: Address : | B5: 27A National Highway, Platero, Biñan City, Laguna | I5: **** Nothing follows **** | K5: =J5*G5 -> 0 | M5: in excess of 7 lines | P5: =J5*0.12 -> 0 | Q5: =J5+P5 -> 0 | R5: =Q5*0.95 -> 0
A6: Business Style : | F6: Editable | K6: =J6*G6 -> 0 | M6: use client's PO#
A7: Amount in Figure | B7: =SUM(B16) -> 6937.5 | F7: Undeditable | K7: =J7*G7 -> 0
A8: Amount in Words (line 1) | B8: Six Thousand Nine Hundred Thirty Seven & 50/100 | F8: limit text to yellow line | K8: =J8*G8 -> 0 | M8: For giving discounts
A9: Amount in Words (line 2) | F9: limit text to yellow line | K9: =J9*G9 -> 0 | M9: Discounted Price
A10: In partial/full payment of | B10: PO No. 11014 | F10: Editable | I10: Total Sales | K10: =SUM(K3:K9) -> 7000 | M10: =#REF! -> #REF!
A11: Total Sales | B11: =SUM(K10) -> 7000 | F11: Undeditable
A12: VAT Rate | B12: 12 | C12: % | F12: Editable
A13: Less VAT | B13: =SUM(B11*B12/100)/(1+(B12/100)) -> 750 | F13: Undeditable | G13: For Delivery Receipt use only
A14: EWT Rate | B14: 1 | C14: % | F14: Override if needed | G14: Qty | H14: pc | I14: Description
A15: Less Witholding Tax | B15: =SUM(B11-B13)*(B14/100) -> 62.5 | F15: Override if needed | G15: =G3 -> 300 | H15: =H3 -> Pcs | I15: =I3 -> 6" TDC Cleat Material: G.I.
A16: Net Collectible Amount | B16: =SUM(B11-B15) -> 6937.5 | F16: Undeditable | G16: =G4 -> 500 | H16: =H4 -> Pcs | I16: =I4 -> Angle Corner Material:G.I. / GA20
A17: VAT Exempt Sales | B17: 0 | F17: Override if needed | I17: =I5 -> **** Nothing follows **** | M17: For Delivery Receipt
A18: Zero Rated Sales | B18: 0 | F18: Override if needed | I18: =I6 -> 0 | M18: up to 16 lines only
M19: in excess of 16 lines
B20: Legend | M20: use separate
C21: -- | D21: Editable | M21: Delivery Receipt
C22: -- | D22: Uneditable
C23: -- | D23: Proceed with caution
A26: CAUTION!!!
A27: Make a client copy of this file before editing. Failure to comply will
A28: result to unexpected irregularities in the application. If this happen
A29: contact the administrator. Observe instructions in using thie application.
A30: Never edit this unless necessary and with permission to administrator
I32: 56704.82
I34: 28352.41
I35: 27846.12
I36: =SUM(I34:I35) -> 56198.53

Sheet SI
B1: =Input!B3 -> TRUE-TEMP CORPORATION | J1: =Input!B2 -> October 13, 2026
B2: =Input!B5 -> 27A National Highway, Platero, Biñan City, Laguna
E3: =Input!B4 -> 216-506-486-00000
A7: =Input!G3 -> 300 | B7: Pcs | C7: =Input!I3 -> 6" TDC Cleat Material: G.I. | J7: =Input!J3 -> 10 | K7: =Input!K3 -> 3000
A8: =Input!G4 -> 500 | B8: Pcs | C8: =Input!I4 -> Angle Corner Material:G.I. / GA20 | J8: =Input!J4 -> 8 | K8: =Input!K4 -> 4000
C9: =Input!I5 -> **** Nothing follows **** | J9: =Input!J5 -> 0 | K9: =Input!K5 -> 0
J10: =Input!J6 -> 0 | K10: =Input!K6 -> 0
J11: =Input!J7 -> 0 | K11: =Input!K7 -> 0
J12: =Input!J8 -> 0 | K12: =Input!K8 -> 0
J13: =Input!J9 -> 0 | K13: =Input!K9 -> 0
K14: =Input!B11 -> 7000
K15: =Input!B13 -> 750
E16: =SUM(K16) -> 6250 | K16: =K14-K15 -> 6250
E17: =Input!B17 -> 0
E18: =Input!B18 -> 0
E19: =SUM(K15) -> 750
K20: =K14 -> 7000

Sheet DR
B1: =Input!B3 -> TRUE-TEMP CORPORATION | I1: =Input!B2 -> October 13, 2026
B2: =Input!B4 -> 216-506-486-00000
B3: =Input!B5 -> 27A National Highway, Platero, Biñan City, Laguna
A5: =Input!G15 -> 300 | B5: Pcs | C5: =Input!I15 -> 6" TDC Cleat Material: G.I.
A6: =Input!G16 -> 500 | B6: Pcs | C6: =Input!I16 -> Angle Corner Material:G.I. / GA20
C7: =Input!I17 -> **** Nothing follows ****

Sheet CR
L4: =Input!B2 -> October 13, 2026
B5: =Input!B11 -> 7000 | C5: =Input!B11 -> 7000 | I5: =Input!B3 -> TRUE-TEMP CORPORATION
B6: =Input!B15 -> 62.5
B7: =B5-B6 -> 6937.5 | C7: =C5-C6 -> 7000 | F7: =Input!B5 -> 27A National Highway, Platero, Biñan City, Laguna
F8: =Input!B6 -> 0 | L8: =Input!B4 -> 216-506-486-00000
G10: =Input!B8 -> Six Thousand Nine Hundred Thirty Seven & 50/100
E12: - | L12: =B13 -> 6937.5
B13: =B7 -> 6937.5
G14: =Input!B10 -> PO No. 11014
